README.rst
setup.py
ripple/__init__.py
ripple/client.py
ripple/datastructures.py
ripple/serialize.py
ripple/sign.py
ripple_python.egg-info/PKG-INFO
ripple_python.egg-info/SOURCES.txt
ripple_python.egg-info/dependency_links.txt
ripple_python.egg-info/requires.txt
ripple_python.egg-info/top_level.txt
ripple_python.egg-info/zip-safe
tests/__init__.py
tests/test_datastructures.py
tests/test_serialize.py
tests/test_sign.py
tests/test_transaction_parsing.py