Metadata-Version: 1.1
Name: ripple-python
Version: 0.2.8
Summary: Python routines for the Ripple payment network
Home-page: https://github.com/miracle2k/ripple-python
Author: Michael Elsdörfer
Author-email: michael@elsdoerfer.com
License: BSD
Platform: UNKNOWN
Classifier: Development Status :: 3 - Alpha
Classifier: Programming Language :: Python :: 3.3
Classifier: License :: OSI Approved :: BSD License
